README.md
setup.py
unipixel/__init__.py
unipixel/unipixel.py
unipixel.egg-info/PKG-INFO
unipixel.egg-info/SOURCES.txt
unipixel.egg-info/dependency_links.txt
unipixel.egg-info/requires.txt
unipixel.egg-info/top_level.txt