Metadata-Version: 2.1
Name: unipixel
Version: 1.0.0
Summary: A testing utility for applications that would use the adafruit-circuitpython-neopixel package
Home-page: https://github.com/razerfish/unipixel
Author: Fiona Wilson
Author-email: fiona@razerfish.dev
License: UNKNOWN
Project-URL: Source Code, https://github.com/Razerfish/unipixel
Project-URL: Bug Tracker, https://github.com/Razerfish/unipixel/issues
Platform: UNKNOWN
Classifier: Development Status :: 5 - Production/Stable
Classifier: Intended Audience :: Developers
Classifier: License :: OSI Approved :: MIT License
Classifier: Natural Language :: English
Classifier: Programming Language :: Python
Classifier: Programming Language :: Python :: 3
Classifier: Programming Language :: Python :: 3.5
Classifier: Programming Language :: Python :: 3.6
Classifier: Programming Language :: Python :: 3.7
Classifier: Programming Language :: Python :: 3.8
Requires-Python: >=3.5
Provides-Extra: dev
Provides-Extra: lint
Provides-Extra: test
